cakemix/__init__.py
cakemix/excel.py
cakemix/extract.py
cakemix/list.py
cakemix/web.py
cakemix-0.0.2.dist-info/LICENCE
cakemix-0.0.2.dist-info/METADATA
cakemix-0.0.2.dist-info/WHEEL
cakemix-0.0.2.dist-info/top_level.txt
cakemix-0.0.2.dist-info/RECORD
