Metadata-Version: 2.1
Name: cakemix
Version: 0.0.2
Summary: Python library to open Office documents, Excel spreadsheets, automate the data analysis and making presentations
Home-page: https://github.com/varlmes/cakemix
Author: Mesut Varlioglu, PhD
Author-email: varlioglu@gmail.com
License: UNKNOWN
Platform: UNKNOWN
Classifier: Programming Language :: Python :: 3
Classifier: License :: OSI Approved :: MIT License
Classifier: Operating System :: OS Independent
Requires-Dist: bs4
Requires-Dist: matplotlib
Requires-Dist: numpy
Requires-Dist: xlrd
